donelist.py
donelist-0.1.dist-info/METADATA
donelist-0.1.dist-info/WHEEL
donelist-0.1.dist-info/entry_points.txt
donelist-0.1.dist-info/top_level.txt
donelist-0.1.dist-info/RECORD
