Metadata-Version: 2.1
Name: donelist
Version: 0.1
Requires-Dist: requests
